README.md
src/xwformats_wrapper.py
xwformats-0.1.0.1.dist-info/METADATA
xwformats-0.1.0.1.dist-info/WHEEL
xwformats-0.1.0.1.dist-info/licenses/LICENSE
xwformats-0.1.0.1.dist-info/RECORD
