Metadata-Version: 2.4
Name: xwformats
Version: 0.1.0.1
Summary: Convenience wrapper for exonware-xwformats - provides 'import xwformats' alias
Project-URL: Homepage, https://exonware.com
Project-URL: Repository, https://github.com/exonware/xwformats
Project-URL: Documentation, https://github.com/exonware/xwformats#readme
Author-email: "Eng. Muhammad AlShehri" <connect@exonware.com>
License: MIT
License-File: LICENSE
Keywords: avro,enterprise,exonware,formats,hdf5,netcdf,parquet,protobuf,scientific,serialization,thrift
Classifier: Development Status :: 4 - Beta
Classifier: Intended Audience :: Developers
Classifier: Intended Audience :: Science/Research
Classifier: License :: OSI Approved :: MIT License
Classifier: Operating System :: OS Independent
Classifier: Programming Language :: Python :: 3
Classifier: Programming Language :: Python :: 3.12
Classifier: Topic :: Scientific/Engineering
Classifier: Topic :: Software Development :: Libraries :: Python Modules
Requires-Python: >=3.12
Requires-Dist: exonware-xwformats
Provides-Extra: full
Requires-Dist: exonware-xwformats[full]; extra == 'full'
Provides-Extra: lazy
Requires-Dist: exonware-xwformats[lazy]; extra == 'lazy'
